spectralign/__init__.py
spectralign/affine.py
spectralign/funcs.py
spectralign/image.py
spectralign/placement.py
spectralign/render.py
spectralign/renderaffine.py
spectralign/swim.py
spectralign-0.4.2.dist-info/licenses/LICENSE
spectralign-0.4.2.dist-info/METADATA
spectralign-0.4.2.dist-info/WHEEL
spectralign-0.4.2.dist-info/top_level.txt
spectralign-0.4.2.dist-info/RECORD
