Metadata-Version: 2.4
Name: spectralign
Version: 0.4.2
Summary: Spectral methods for image alignment
Author-email: Daniel Wagenaar <daw@caltech.edu>
License-Expression: GPL-3.0-or-later
Project-URL: Homepage, https://github.com/wagenadl/spectralign
Classifier: Programming Language :: Python :: 3
Classifier: Operating System :: OS Independent
Requires-Python: >=3.12
License-File: LICENSE
Requires-Dist: numpy
Requires-Dist: scipy
Requires-Dist: opencv-python
Dynamic: license-file
